MANIFEST.in
setup.py
asset_bundles/__init__.py
asset_bundles/bundle.py
asset_bundles/yuicompressor-2.4.6.jar
asset_bundles.egg-info/PKG-INFO
asset_bundles.egg-info/SOURCES.txt
asset_bundles.egg-info/dependency_links.txt
asset_bundles.egg-info/requires.txt
asset_bundles.egg-info/top_level.txt
asset_bundles/management/__init__.py
asset_bundles/management/commands/__init__.py
asset_bundles/management/commands/create_bundles.py
asset_bundles/templatetags/__init__.py
asset_bundles/templatetags/assets.py