Metadata-Version: 1.0
Name: asset-bundles
Version: 0.1.3
Summary: simple clone of django_assets compatible with django 1.3 and staticfiles
Home-page: UNKNOWN
Author: Viktor Kotseruba
Author-email: barbuzaster@gmail.com
License: MIT
Keywords: web django
Platform: UNKNOWN
